bridgic/llms/vllm/__init__.py
bridgic/llms/vllm/vllm_server_llm.py
bridgic_llms_vllm-0.1.0.dist-info/METADATA
bridgic_llms_vllm-0.1.0.dist-info/WHEEL
bridgic_llms_vllm-0.1.0.dist-info/licenses/LICENSE
bridgic_llms_vllm-0.1.0.dist-info/RECORD
